presearch/__init__.py
presearch/__main__.py
presearch/constraints.py
presearch/crawler.py
presearch/presearch.py
presearch/query.py
presearch/tree.py
presearch-0.0.1.dist-info/LICENSE
presearch-0.0.1.dist-info/METADATA
presearch-0.0.1.dist-info/WHEEL
presearch-0.0.1.dist-info/entry_points.txt
presearch-0.0.1.dist-info/top_level.txt
presearch-0.0.1.dist-info/RECORD
