Metadata-Version: 2.1
Name: presearch
Version: 0.0.1
Summary: A tool to syntactically query Python source code
Home-page: https://github.com/dignissimus/presearch
Author: Sam Ezeh
Author-email: sam.z.ezeh@gmail.com
License: UNKNOWN
Project-URL: Bug Tracker, https://github.com/dignissimus/presearch/issues
Platform: UNKNOWN
Classifier: Programming Language :: Python :: 3
Classifier: Operating System :: OS Independent
Requires-Python: >=3.6
License-File: LICENSE
Requires-Dist: termcolor
Requires-Dist: colorama
